torchfitter/__init__.py
torchfitter/_version.py
torchfitter/conventions.py
torchfitter/io.py
torchfitter/testing.py
torchfitter/callbacks/__init__.py
torchfitter/callbacks/_callbacks.py
torchfitter/callbacks/base.py
torchfitter/callbacks/progress/__init__.py
torchfitter/callbacks/regularization/__init__.py
torchfitter/callbacks/scheduling/__init__.py
torchfitter/trainer/__init__.py
torchfitter/trainer/_trainer.py
torchfitter/trainer/_utils.py
torchfitter/utils/__init__.py
torchfitter/utils/convenience.py
torchfitter/utils/data.py
torchfitter/utils/preprocessing.py
torchfitter-4.3.0.dist-info/METADATA
torchfitter-4.3.0.dist-info/WHEEL
torchfitter-4.3.0.dist-info/top_level.txt
torchfitter-4.3.0.dist-info/RECORD
