Metadata-Version: 2.1
Name: torchfitter
Version: 4.3.0
Summary: Trainer to optimize PyTorch models
Author: Alejandro Pérez-Sanjuán
Requires-Python: >=3.7,
Requires-Dist: rich
Requires-Dist: numpy (>=1.20.0)
Requires-Dist: accelerate (>=0.19.0)
Requires-Dist: scikit-learn
Requires-Dist: torchmetrics
Requires-Dist: torch (>=1.6)
